MANIFEST.in
README.md
setup.py
example/__init__.py
example/__main__.py
example/file_system.py
example/system_time.py
thin_cli/__init__.py
thin_cli/_wrappers.py
thin_cli/protocols.py
thin_cli/py.typed
thin_cli.egg-info/PKG-INFO
thin_cli.egg-info/SOURCES.txt
thin_cli.egg-info/dependency_links.txt
thin_cli.egg-info/top_level.txt