Metadata-Version: 2.1
Name: thin-cli
Version: 1.0.4
Summary: A thin command line interface framework.
Home-page: https://github.com/averycowan/lite_cli
Author: Avery Cowan
License: UNKNOWN
Platform: UNKNOWN
